[
  {
    "title": "Recording metrics in-process using MeterListener: System.Diagnostics.Metrics APIs - Part 4",
    "link": "https://andrewlock.net/recording-metrics-in-process-using-meterlistener/",
    "pubDate": "2026-02-24T10:00:00+00:00"
  },
  {
    "title": "Creating standard and \"observable\" instruments: System.Diagnostics.Metrics APIs - Part 3",
    "link": "https://andrewlock.net/creating-standard-and-observable-instruments/",
    "pubDate": "2026-02-17T10:00:00+00:00"
  },
  {
    "title": "Exploring the (underwhelming) System.Diagnostics.Metrics source generators: System.Diagnostics.Metrics APIs - Part 2",
    "link": "https://andrewlock.net/creating-strongly-typed-metics-with-a-source-generator/",
    "pubDate": "2026-02-03T10:00:00+00:00"
  },
  {
    "title": "Creating and consuming metrics with System.Diagnostics.Metrics APIs: System.Diagnostics.Metrics APIs - Part 1",
    "link": "https://andrewlock.net/creating-and-consuming-metrics-with-system-diagnostics-metrics-apis/",
    "pubDate": "2026-01-27T10:00:00+00:00"
  },
  {
    "title": "Making foreach on an IEnumerable allocation-free using reflection and dynamic methods",
    "link": "https://andrewlock.net/making-foreach-on-an-ienumerable-allocation-free-using-reflection-and-dynamic-methods/",
    "pubDate": "2026-01-20T10:00:00+00:00"
  }
]
