[
  {
    "title": "Data API Builder - Get a visual config UI",
    "link": "https://bartwullems.blogspot.com/2026/04/data-api-builder-get-visual-config-ui.html",
    "pubDate": "2026-04-27T05:06:00+00:00"
  },
  {
    "title": "Microsoft Agent Framework- Workflow lifetime",
    "link": "https://bartwullems.blogspot.com/2026/04/microsoft-agent-framework-workflow.html",
    "pubDate": "2026-04-24T05:32:00+00:00"
  },
  {
    "title": "Expose your stored procedures as AI agent tools with DAB 2.0",
    "link": "https://bartwullems.blogspot.com/2026/04/expose-your-stored-procedures-as-ai.html",
    "pubDate": "2026-04-23T07:30:00+00:00"
  },
  {
    "title": "DAB 2.0 Preview: Autoconfiguration with autoentities",
    "link": "https://bartwullems.blogspot.com/2026/04/dab-20-preview-autoconfiguration-with.html",
    "pubDate": "2026-04-21T05:30:00+00:00"
  },
  {
    "title": "Fixing the \"Newer version of Aspire.Hosting.AppHost required\" error",
    "link": "https://bartwullems.blogspot.com/2026/04/fixing-newer-version-of.html",
    "pubDate": "2026-04-20T04:45:00+00:00"
  }
]
