[
  {
    "title": "Part VIII – Evaluations(continued)",
    "link": "https://bartwullems.blogspot.com/2025/09/part-viii-evaluationscontinued.html",
    "pubDate": "2025-09-11T07:21:00.009+02:00"
  },
  {
    "title": "Microsoft.Extensions.AI–Part VIII–Evaluations",
    "link": "https://bartwullems.blogspot.com/2025/09/microsoftextensionsaipart.html",
    "pubDate": "2025-09-10T07:29:00.008+02:00"
  },
  {
    "title": "The prompt as documentation: Should AI-generated code include its origin story?",
    "link": "https://bartwullems.blogspot.com/2025/09/the-prompt-as-documentation-should-ai.html",
    "pubDate": "2025-09-09T07:31:00.017+02:00"
  },
  {
    "title": "Custom chat modes in Github Copilot",
    "link": "https://bartwullems.blogspot.com/2025/09/custom-chat-modes-in-github-copilot.html",
    "pubDate": "2025-09-08T06:48:00.020+02:00"
  },
  {
    "title": "Why rational humans make irrational decisions",
    "link": "https://bartwullems.blogspot.com/2025/09/why-rational-humans-make-irrational.html",
    "pubDate": "2025-09-05T07:56:00.017+02:00"
  }
]
