[
  {
    "title": "Ideological Resistance to Patents, Followed by Reluctant                Pragmatism",
    "link": "https://martinfowler.com/articles/patents-reluctant-pragmatism.html",
    "pubDate": "2026-03-05T13:54:00+00:00"
  },
  {
    "title": "Humans and Agents in Software Engineering Loops",
    "link": "https://martinfowler.com/articles/exploring-gen-ai/humans-and-agents.html",
    "pubDate": "2026-03-04T05:42:00+00:00"
  },
  {
    "title": "Design-First Collaboration",
    "link": "https://martinfowler.com/articles/reduce-friction-ai/design-first-collaboration.html",
    "pubDate": "2026-03-03T04:04:00+00:00"
  },
  {
    "title": "Fragments: February 25",
    "link": "https://martinfowler.com/fragments/2026-02-25.html",
    "pubDate": "2026-02-25T14:56:00+00:00"
  },
  {
    "title": "Knowledge Priming",
    "link": "https://martinfowler.com/articles/reduce-friction-ai/knowledge-priming.html",
    "pubDate": "2026-02-24T14:40:00+00:00"
  }
]
