[
  {
    "title": "Probably the realest thing I ever wrote",
    "link": "https://swizec.com/blog/probably-the-realest-thing-i-ever-wrote/",
    "pubDate": "2026-02-28T22:21:02+00:00"
  },
  {
    "title": "Users buy your service, not your code",
    "link": "https://swizec.com/blog/users-buy-your-service-not-your-code/",
    "pubDate": "2026-02-18T17:01:23+00:00"
  },
  {
    "title": "GeLLMan amnesia",
    "link": "https://swizec.com/blog/ge-ll-man-amnesia/",
    "pubDate": "2026-02-16T22:26:45+00:00"
  },
  {
    "title": "The 3 curves that make a scalable business",
    "link": "https://swizec.com/blog/the-3-curves-that-make-a-scalable-business/",
    "pubDate": "2026-02-10T00:00:00+00:00"
  },
  {
    "title": "In praise of the stacked pull request",
    "link": "https://swizec.com/blog/in-praise-of-the-stacked-pull-request/",
    "pubDate": "2026-02-04T00:00:00+00:00"
  }
]
